{
  "routes": [
    {
      "method": "GET",
      "path": "/moves",
      "handler": "move.find",
      "config": {
        "policies": []
      }
    },
    {
      "method": "GET",
      "path": "/moves/count",
      "handler": "move.count",
      "config": {
        "policies": []
      }
    },
    {
      "method": "GET",
      "path": "/moves/:id",
      "handler": "move.findOne",
      "config": {
        "policies": []
      }
    },
    {
      "method": "POST",
      "path": "/moves",
      "handler": "move.create",
      "config": {
        "policies": []
      }
    },
    {
      "method": "PUT",
      "path": "/moves/:id",
      "handler": "move.update",
      "config": {
        "policies": []
      }
    },
    {
      "method": "DELETE",
      "path": "/moves/:id",
      "handler": "move.delete",
      "config": {
        "policies": []
      }
    }
  ]
}
